{"title":"Moira = OPAF","slug":"moira","date":"2017-12-17T12:39:05.000Z","updated":"2017-12-17T12:43:18.755Z","comments":true,"path":"api/articles/moira.json","photos":["/images/moira.png","/images/moira2.jpg"],"link":"","excerpt":null,"covers":null,"content":"<blockquote>\n<p>Surrender to my will!<br>屈服于我的意志吧！</p>\n</blockquote>\n<p><a href=\"https://www.overbuff.com/heroes/moira\" target=\"_blank\" rel=\"noopener\">OverBuff</a>的数据显示，现在莫伊拉强无敌。</p>\n<p><del>我就是要吸爆源氏的狗头</del></p>\n","categories":[],"tags":[{"name":"Overwatch","slug":"Overwatch","count":1,"path":"api/tags/Overwatch.json"},{"name":"Moira","slug":"Moira","count":1,"path":"api/tags/Moira.json"}]}